[{"jozz":9,"sura_no":7,"sura_name_ar":"الأعرَاف ","aya_no":130,"aya_no_marker":"ﲁ","aya_text":"فَإِذَا جَآءَتْهُمُ اُ۬لْحَسَنَةُ قَالُواْ لَنَا هَٰذِهِۦۖ وَإِن تُصِبْهُمْ سَيِّئَةٞ يَطَّيَّرُواْ بِمُوس۪ىٰ وَمَن مَّعَهُۥٓۖ أَلَآ إِنَّمَا طَٰٓئِرُهُمْ عِندَ اَ۬للَّهِۖ وَلَٰكِنَّ أَكْثَرَهُمْ لَا يَعْلَمُونَۖ"},{"jozz":9,"sura_no":7,"sura_name_ar":"الأعرَاف ","aya_no":131,"aya_no_marker":"ﲂ","aya_text":"۞ وَقَالُواْ مَهْمَا تَاتِنَا بِهِۦ مِنَ اٰيَةٖ لِّتَسْحَرَنَا بِهَا فَمَا نَحْنُ لَكَ بِمُومِنِينَۖ"},{"jozz":9,"sura_no":7,"sura_name_ar":"الأعرَاف ","aya_no":132,"aya_no_marker":"ﲃ","aya_text":"فَأَرْسَلْنَا عَلَيْهِمُ اُ۬لطُّوفَانَ وَالْجَرَادَ وَالْقُمَّلَ وَالضَّفَادِعَ وَالدَّمَ ءَايَٰتٖ مُّفَصَّلَٰتٖ فَاسْتَكْبَرُواْ وَكَانُواْ قَوْماٗ مُّجْرِمِينَۖ"},{"jozz":9,"sura_no":7,"sura_name_ar":"الأعرَاف ","aya_no":133,"aya_no_marker":"ﲄ","aya_text":"وَلَمَّا وَقَعَ عَلَيْهِمُ اُ۬لرِّجْزُ قَالُواْ يَٰمُوسَى اَ۟دْعُ لَنَا رَبَّكَ بِمَا عَهِدَ عِندَكَ لَئِن كَشَفْتَ عَنَّا اَ۬لرِّجْزَ لَنُومِنَنَّ لَكَ وَلَنُرْسِلَنَّ مَعَكَ بَنِےٓ إِسْرَآءِيلَۖ"},{"jozz":9,"sura_no":7,"sura_name_ar":"الأعرَاف ","aya_no":134,"aya_no_marker":"ﲅ","aya_text":"فَلَمَّا كَشَفْنَا عَنْهُمُ اُ۬لرِّجْزَ إِلَىٰٓ أَجَلٍ هُم بَٰلِغُوهُ إِذَا هُمْ يَنكُثُونَۖ"},{"jozz":9,"sura_no":7,"sura_name_ar":"الأعرَاف ","aya_no":135,"aya_no_marker":"ﲆ","aya_text":"فَانتَقَمْنَا مِنْهُمْ فَأَغْرَقْنَٰهُمْ فِے اِ۬لْيَمِّ بِأَنَّهُمْ كَذَّبُواْ بِـَٔايَٰتِنَا وَكَانُواْ عَنْهَا غَٰفِلِينَۖ"},{"jozz":9,"sura_no":7,"sura_name_ar":"الأعرَاف ","aya_no":136,"aya_no_marker":"ﲇ","aya_text":"وَأَوْرَثْنَا اَ۬لْقَوْمَ اَ۬لذِينَ كَانُواْ يُسْتَضْعَفُونَ مَشَٰرِقَ اَ۬لَارْضِ وَمَغَٰرِبَهَا اَ۬لتِے بَٰرَكْنَا فِيهَاۖ وَتَمَّتْ كَلِمَةُ رَبِّكَ اَ۬لْحُسْن۪ىٰ عَلَىٰ بَنِےٓ إِسْرَآءِيلَ"},{"jozz":9,"sura_no":7,"sura_name_ar":"الأعرَاف ","aya_no":137,"aya_no_marker":"ﲈ","aya_text":"بِمَا صَبَرُواْۖ وَدَمَّرْنَا مَا كَانَ يَصْنَعُ فِرْعَوْنُ وَقَوْمُهُۥ وَمَا كَانُواْ يَعْرِشُونَۖ"}]