[{"jozz":29,"sura_no":69,"sura_name_ar":"الحَاقة ","aya_no":36,"aya_no_marker":"ﰣ","aya_text":"وَلَا طَعَامٌ اِلَّا مِنْ غِسْلِينٖ"},{"jozz":29,"sura_no":69,"sura_name_ar":"الحَاقة ","aya_no":37,"aya_no_marker":"ﰤ","aya_text":"لَّا يَاكُلُهُۥٓ إِلَّا اَ۬لْخَٰطِـُٔونَۖ"},{"jozz":29,"sura_no":69,"sura_name_ar":"الحَاقة ","aya_no":38,"aya_no_marker":"ﰥ","aya_text":"فَلَآ أُقْسِمُ بِمَا تُبْصِرُونَ"},{"jozz":29,"sura_no":69,"sura_name_ar":"الحَاقة ","aya_no":39,"aya_no_marker":"ﰦ","aya_text":"وَمَا لَا تُبْصِرُونَ"},{"jozz":29,"sura_no":69,"sura_name_ar":"الحَاقة ","aya_no":40,"aya_no_marker":"ﰧ","aya_text":"إِنَّهُۥ لَقَوْلُ رَسُولٖ كَرِيمٖ"},{"jozz":29,"sura_no":69,"sura_name_ar":"الحَاقة ","aya_no":41,"aya_no_marker":"ﰨ","aya_text":"وَمَا هُوَ بِقَوْلِ شَاعِرٖ قَلِيلاٗ مَّا تُومِنُونَ"},{"jozz":29,"sura_no":69,"sura_name_ar":"الحَاقة ","aya_no":42,"aya_no_marker":"ﰩ","aya_text":"وَلَا بِقَوْلِ كَاهِنٖۖ قَلِيلاٗ مَّا تَذَّكَّرُونَۖ"},{"jozz":29,"sura_no":69,"sura_name_ar":"الحَاقة ","aya_no":43,"aya_no_marker":"ﰪ","aya_text":"تَنزِيلٞ مِّن رَّبِّ اِ۬لْعَٰلَمِينَۖ"},{"jozz":29,"sura_no":69,"sura_name_ar":"الحَاقة ","aya_no":44,"aya_no_marker":"ﰫ","aya_text":"وَلَوْ تَقَوَّلَ عَلَيْنَا بَعْضَ اَ۬لَاقَاوِيلِ"},{"jozz":29,"sura_no":69,"sura_name_ar":"الحَاقة ","aya_no":45,"aya_no_marker":"ﰬ","aya_text":"لَأَخَذْنَا مِنْهُ بِالْيَمِينِ"},{"jozz":29,"sura_no":69,"sura_name_ar":"الحَاقة ","aya_no":46,"aya_no_marker":"ﰭ","aya_text":"ثُمَّ لَقَطَعْنَا مِنْهُ اُ۬لْوَتِينَ"},{"jozz":29,"sura_no":69,"sura_name_ar":"الحَاقة ","aya_no":47,"aya_no_marker":"ﰮ","aya_text":"فَمَا مِنكُم مِّنَ اَحَدٍ عَنْهُ حَٰجِزِينَۖ"},{"jozz":29,"sura_no":69,"sura_name_ar":"الحَاقة ","aya_no":48,"aya_no_marker":"ﰯ","aya_text":"وَإِنَّهُۥ لَتَذْكِرَةٞ لِّلْمُتَّقِينَۖ"},{"jozz":29,"sura_no":69,"sura_name_ar":"الحَاقة ","aya_no":49,"aya_no_marker":"ﰰ","aya_text":"وَإِنَّا لَنَعْلَمُ أَنَّ مِنكُم مُّكَذِّبِينَۖ"},{"jozz":29,"sura_no":69,"sura_name_ar":"الحَاقة ","aya_no":50,"aya_no_marker":"ﰱ","aya_text":"وَإِنَّهُۥ لَحَسْرَةٌ عَلَى اَ۬لْكٰ۪فِرِينَۖ"},{"jozz":29,"sura_no":69,"sura_name_ar":"الحَاقة ","aya_no":51,"aya_no_marker":"ﰲ","aya_text":"وَإِنَّهُۥ لَحَقُّ اُ۬لْيَقِينِۖ"},{"jozz":29,"sura_no":69,"sura_name_ar":"الحَاقة ","aya_no":52,"aya_no_marker":"ﰳ","aya_text":"فَسَبِّحْ بِاسْمِ رَبِّكَ اَ۬لْعَظِيمِۖ"},{"jozz":29,"sura_no":70,"sura_name_ar":"المَعَارج ","aya_no":1,"aya_no_marker":"ﰀ","aya_text":"سَالَ سَآئِلُۢ بِعَذَابٖ وَاقِعٖ"},{"jozz":29,"sura_no":70,"sura_name_ar":"المَعَارج ","aya_no":2,"aya_no_marker":"ﰁ","aya_text":"لِّلْكٰ۪فِرِينَ لَيْسَ لَهُۥ دَافِعٞ"},{"jozz":29,"sura_no":70,"sura_name_ar":"المَعَارج ","aya_no":3,"aya_no_marker":"ﰂ","aya_text":"مِّنَ اَ۬للَّهِ ذِے اِ۬لْمَعَارِجِۖ"},{"jozz":29,"sura_no":70,"sura_name_ar":"المَعَارج ","aya_no":4,"aya_no_marker":"ﰃ","aya_text":"تَعْرُجُ اُ۬لْمَلَٰٓئِكَةُ وَالرُّوحُ إِلَيْهِ فِے يَوْمٖ كَانَ مِقْدَارُهُۥ خَمْسِينَ أَلْفَ سَنَةٖۖ"},{"jozz":29,"sura_no":70,"sura_name_ar":"المَعَارج ","aya_no":5,"aya_no_marker":"ﰄ","aya_text":"فَاصْبِرْ صَبْراٗ جَمِيلاًۖ"},{"jozz":29,"sura_no":70,"sura_name_ar":"المَعَارج ","aya_no":6,"aya_no_marker":"ﰅ","aya_text":"اِنَّهُمْ يَرَوْنَهُۥ بَعِيداٗ"},{"jozz":29,"sura_no":70,"sura_name_ar":"المَعَارج ","aya_no":7,"aya_no_marker":"ﰆ","aya_text":"وَنَر۪يٰهُ قَرِيباٗۖ"},{"jozz":29,"sura_no":70,"sura_name_ar":"المَعَارج ","aya_no":8,"aya_no_marker":"ﰇ","aya_text":"يَوْمَ تَكُونُ اُ۬لسَّمَآءُ كَالْمُهْلِ"},{"jozz":29,"sura_no":70,"sura_name_ar":"المَعَارج ","aya_no":9,"aya_no_marker":"ﰈ","aya_text":"وَتَكُونُ اُ۬لْجِبَالُ كَالْعِهْنِ"},{"jozz":29,"sura_no":70,"sura_name_ar":"المَعَارج ","aya_no":10,"aya_no_marker":"ﰉ","aya_text":"وَلَا يَسْـَٔلُ حَمِيمٌ حَمِيماٗ"}]