[{"jozz":27,"sura_no":53,"sura_name_ar":"النَّجم","aya_no":27,"aya_no_marker":"ﰚ","aya_text":"إِنَّ ٱلَّذِينَ لَا يُؤۡمِنُونَ بِٱلۡأٓخِرَةِ لَيُسَمُّونَ ٱلۡمَلَٰٓئِكَةَ تَسۡمِيَةَ ٱلۡأُنثَىٰ"},{"jozz":27,"sura_no":53,"sura_name_ar":"النَّجم","aya_no":28,"aya_no_marker":"ﰛ","aya_text":"وَمَا لَهُم بِهِۦ مِنۡ عِلۡمٍۖ إِن يَتَّبِعُونَ إِلَّا ٱلظَّنَّۖ وَإِنَّ ٱلظَّنَّ لَا يُغۡنِي مِنَ ٱلۡحَقِّ شَيۡـٔٗا"},{"jozz":27,"sura_no":53,"sura_name_ar":"النَّجم","aya_no":29,"aya_no_marker":"ﰜ","aya_text":"فَأَعۡرِضۡ عَن مَّن تَوَلَّىٰ عَن ذِكۡرِنَا وَلَمۡ يُرِدۡ إِلَّا ٱلۡحَيَوٰةَ ٱلدُّنۡيَا"},{"jozz":27,"sura_no":53,"sura_name_ar":"النَّجم","aya_no":30,"aya_no_marker":"ﰝ","aya_text":"ذَٰلِكَ مَبۡلَغُهُم مِّنَ ٱلۡعِلۡمِۚ إِنَّ رَبَّكَ هُوَ أَعۡلَمُ بِمَن ضَلَّ عَن سَبِيلِهِۦ وَهُوَ أَعۡلَمُ بِمَنِ ٱهۡتَدَىٰ"},{"jozz":27,"sura_no":53,"sura_name_ar":"النَّجم","aya_no":31,"aya_no_marker":"ﰞ","aya_text":"وَلِلَّهِ مَا فِي ٱلسَّمَٰوَٰتِ وَمَا فِي ٱلۡأَرۡضِ لِيَجۡزِيَ ٱلَّذِينَ أَسَٰٓـُٔواْ بِمَا عَمِلُواْ وَيَجۡزِيَ ٱلَّذِينَ أَحۡسَنُواْ بِٱلۡحُسۡنَى"},{"jozz":27,"sura_no":53,"sura_name_ar":"النَّجم","aya_no":32,"aya_no_marker":"ﰟ","aya_text":"ٱلَّذِينَ يَجۡتَنِبُونَ كَبَٰٓئِرَ ٱلۡإِثۡمِ وَٱلۡفَوَٰحِشَ إِلَّا ٱللَّمَمَۚ إِنَّ رَبَّكَ وَٰسِعُ ٱلۡمَغۡفِرَةِۚ هُوَ أَعۡلَمُ بِكُمۡ إِذۡ أَنشَأَكُم مِّنَ ٱلۡأَرۡضِ وَإِذۡ أَنتُمۡ أَجِنَّةٞ فِي بُطُونِ أُمَّهَٰتِكُمۡۖ فَلَا تُزَكُّوٓاْ أَنفُسَكُمۡۖ هُوَ أَعۡلَمُ بِمَنِ ٱتَّقَىٰٓ"},{"jozz":27,"sura_no":53,"sura_name_ar":"النَّجم","aya_no":33,"aya_no_marker":"ﰠ","aya_text":"أَفَرَءَيۡتَ ٱلَّذِي تَوَلَّىٰ"},{"jozz":27,"sura_no":53,"sura_name_ar":"النَّجم","aya_no":34,"aya_no_marker":"ﰡ","aya_text":"وَأَعۡطَىٰ قَلِيلٗا وَأَكۡدَىٰٓ"},{"jozz":27,"sura_no":53,"sura_name_ar":"النَّجم","aya_no":35,"aya_no_marker":"ﰢ","aya_text":"أَعِندَهُۥ عِلۡمُ ٱلۡغَيۡبِ فَهُوَ يَرَىٰٓ"},{"jozz":27,"sura_no":53,"sura_name_ar":"النَّجم","aya_no":36,"aya_no_marker":"ﰣ","aya_text":"أَمۡ لَمۡ يُنَبَّأۡ بِمَا فِي صُحُفِ مُوسَىٰ"},{"jozz":27,"sura_no":53,"sura_name_ar":"النَّجم","aya_no":37,"aya_no_marker":"ﰤ","aya_text":"وَإِبۡرَٰهِيمَ ٱلَّذِي وَفَّىٰٓ"},{"jozz":27,"sura_no":53,"sura_name_ar":"النَّجم","aya_no":38,"aya_no_marker":"ﰥ","aya_text":"أَلَّا تَزِرُ وَازِرَةٞ وِزۡرَ أُخۡرَىٰ"},{"jozz":27,"sura_no":53,"sura_name_ar":"النَّجم","aya_no":39,"aya_no_marker":"ﰦ","aya_text":"وَأَن لَّيۡسَ لِلۡإِنسَٰنِ إِلَّا مَا سَعَىٰ"},{"jozz":27,"sura_no":53,"sura_name_ar":"النَّجم","aya_no":40,"aya_no_marker":"ﰧ","aya_text":"وَأَنَّ سَعۡيَهُۥ سَوۡفَ يُرَىٰ"},{"jozz":27,"sura_no":53,"sura_name_ar":"النَّجم","aya_no":41,"aya_no_marker":"ﰨ","aya_text":"ثُمَّ يُجۡزَىٰهُ ٱلۡجَزَآءَ ٱلۡأَوۡفَىٰ"},{"jozz":27,"sura_no":53,"sura_name_ar":"النَّجم","aya_no":42,"aya_no_marker":"ﰩ","aya_text":"وَأَنَّ إِلَىٰ رَبِّكَ ٱلۡمُنتَهَىٰ"},{"jozz":27,"sura_no":53,"sura_name_ar":"النَّجم","aya_no":43,"aya_no_marker":"ﰪ","aya_text":"وَأَنَّهُۥ هُوَ أَضۡحَكَ وَأَبۡكَىٰ"},{"jozz":27,"sura_no":53,"sura_name_ar":"النَّجم","aya_no":44,"aya_no_marker":"ﰫ","aya_text":"وَأَنَّهُۥ هُوَ أَمَاتَ وَأَحۡيَا"}]